setup.py
fast/__init__.py
fast/fast01.py
fast/fast02.py
lightning001.egg-info/PKG-INFO
lightning001.egg-info/SOURCES.txt
lightning001.egg-info/dependency_links.txt
lightning001.egg-info/top_level.txt