Metadata-Version: 2.1
Name: lightning001
Version: 1.0.1
Summary: This is first module
Author: pgog
Author-email: 2720060895@qq.com
License: UNKNOWN
Platform: UNKNOWN
